simpletrans/__init__.py
simpletrans/__main__.py
simpletrans/database_interaction.py
simpletrans/hapi_wrapper.py
simpletrans/isa.py
simpletrans/optical_depth_functions.py
simpletrans/plank.py
simpletrans/radiative_transfer.py
SimpleTrans-0.2.5.dist-info/METADATA
SimpleTrans-0.2.5.dist-info/WHEEL
SimpleTrans-0.2.5.dist-info/entry_points.txt
SimpleTrans-0.2.5.dist-info/top_level.txt
SimpleTrans-0.2.5.dist-info/RECORD
